pycord18n/__init__.py
pycord18n/extension.py
pycord18n/i18n.py
pycord18n/language.py
pycord18n-1.0.3.dist-info/LICENSE
pycord18n-1.0.3.dist-info/METADATA
pycord18n-1.0.3.dist-info/WHEEL
pycord18n-1.0.3.dist-info/top_level.txt
pycord18n-1.0.3.dist-info/RECORD
