Metadata-Version: 2.1
Name: pycord18n
Version: 1.0.3
Summary: Localization for the discord.py fork, pycord
Home-page: https://github.com/YoungTrep/pycord18n
Author: YoungTrep, Ghoul
Author-email: youngtrep.business@gmail.com
License: GNU
Project-URL: Issue Tracker, https://github.com/YoungTrep/pycord18n/issues
Platform: UNKNOWN
Classifier: Programming Language :: Python :: 3
Classifier: License :: OSI Approved :: GNU General Public License v3 (GPLv3)
Classifier: Operating System :: OS Independent
Classifier: Natural Language :: English
Requires-Python: >=3.6
License-File: LICENSE
Requires-Dist: py-cord (==2.0.0a3861+g2d747f8f)
